<?xml version="1.0"?>
<Container name="menu" size="1024,768"  position_technique="automatic">
	<Icon name="background" />
	<Icon image="content/gui/images/background/mainmenu/wheel.png" position="212,44" />
	<Icon image="content/gui/images/logos/fife.png" position="22,20" />
	<Icon image="content/gui/images/logos/sdl.png" position="883,20" />
	<Icon image="content/gui/images/logos/opengl.png" position="880,100" />

	<Label name="version_label" text="Unknown Horizons" position="735,735" />

	<!-- clockwise, starting at 0 degree -->
	<Label name="start"  text="Singleplayer"  position="531,100"
		comment="Opens widget to create singleplayer games (campaigns, scenarios, random maps, free play)" />
	<Icon image="content/gui/images/background/oa_startmenu_buttonbg.png" position="457,144" />
	<ImageButton name="startSingle"
		position="488,169"
		is_focusable="0"
		up_image="content/gui/icons/mainmenu/compass_bw.png"
		down_image="content/gui/icons/mainmenu/compass.png"
		hover_image="content/gui/icons/mainmenu/compass.png" />

	<Label name="start_multi"  text="Multiplayer"  position="680,200"
		comment="Opens widget to join or create multiplayer games" />
	<Icon image="content/gui/images/background/oa_startmenu_buttonbg.png" position="566,188" />
	<ImageButton name="startMulti"
		position="593,211"
		is_focusable="0"
		up_image="content/gui/icons/mainmenu/multiplayer_bw.png"
		down_image="content/gui/icons/mainmenu/multiplayer.png"
		hover_image="content/gui/icons/mainmenu/multiplayer.png" />

	<Label name="settings"  text="Settings"  position="710,365"  comment="Main / in-game menu entry" />
	<Icon image="content/gui/images/background/oa_startmenu_buttonbg.png" position="612,298" />
	<ImageButton name="settingsLink"
		position="637,323"
		is_focusable="0"
		up_image="content/gui/icons/mainmenu/gears_bw.png"
		down_image="content/gui/icons/mainmenu/gears.png"
		hover_image="content/gui/icons/mainmenu/gears.png" />

	<Label name="help"  text="Help"  position="590,518"  comment="Main / in-game menu entry" />
	<Icon image="content/gui/images/background/oa_startmenu_buttonbg.png" position="566,406" />
	<ImageButton name="helpLink"
		position="593,431"
		is_focusable="0"
		up_image="content/gui/icons/mainmenu/help_bw.png"
		down_image="content/gui/icons/mainmenu/help.png"
		hover_image="content/gui/icons/mainmenu/help.png" />

	<Label name="quit" text="Quit" position="442,565"  comment="Completely shut down UH" />
	<Icon image="content/gui/images/background/oa_startmenu_buttonbg.png" position="457,452" />
	<ImageButton name="closeButton"
		position="484,478"
		is_focusable="0"
		up_image="content/gui/icons/mainmenu/door_bw.png"
		down_image="content/gui/icons/mainmenu/door.png"
		hover_image="content/gui/icons/mainmenu/door.png" />

	<Label name="chimebell" text="Attention please!" position="190,500" />
	<Icon image="content/gui/images/background/oa_startmenu_buttonbg.png" position="349,406" />
	<ImageButton name="dead_link"
		position="376,431"
		is_focusable="0"
		up_image="content/gui/icons/mainmenu/bell_bw.png"
		down_image="content/gui/icons/mainmenu/bell.png"
		hover_image="content/gui/icons/mainmenu/bell.png" />

	<Label name="credits" text="Credits" position="165,365"/>
	<Icon image="content/gui/images/background/oa_startmenu_buttonbg.png" position="302,298" />
	<ImageButton name="creditsLink"
		position="328,321"
		is_focusable="0"
		up_image="content/gui/icons/mainmenu/log_bw.png"
		down_image="content/gui/icons/mainmenu/log.png"
		hover_image="content/gui/icons/mainmenu/log.png" />

	<Label name="loadgame" text="Load game" position="190,162"  comment="Open a widget to select which game to load" />
	<Icon image="content/gui/images/background/oa_startmenu_buttonbg.png" position="350,188" />
	<ImageButton name="loadgameButton"
		position="376,212"
		is_focusable="0"
		up_image="content/gui/icons/mainmenu/load_bw.png"
		down_image="content/gui/icons/mainmenu/load.png"
		hover_image="content/gui/icons/mainmenu/load.png" />

</Container>
